llm_py/__init__.py
llm_py/component.py
llm_py/configs.py
llm_py/model.py
llm_py/components/__init__.py
llm_py/components/activation/__init__.py
llm_py/components/activation/swiglu.py
llm_py/components/attention/__init__.py
llm_py/components/attention/cross_attention.py
llm_py/components/attention/gqa.py
llm_py/components/attention/mqa.py
llm_py/components/attention/self_attention.py
llm_py/components/attention/sliding_window.py
llm_py/components/common/residual.py
llm_py/components/embedding/__init__.py
llm_py/components/embedding/embedding.py
llm_py/components/ffn/__init__.py
llm_py/components/ffn/feed_forward.py
llm_py/components/heads/__init__.py
llm_py/components/heads/lm_head.py
llm_py/components/heads/moe_head.py
llm_py/components/norm/__init__.py
llm_py/components/norm/layer_norm.py
llm_py/components/norm/rms_norm.py
llm_py/components/pos/__init__.py
llm_py/components/pos/alibi.py
llm_py/components/pos/learned.py
llm_py/components/pos/relative.py
llm_py/components/pos/rotary.py
llm_py/components/pos/sinusoidal.py
llm_dot_py-0.1.2.dist-info/METADATA
llm_dot_py-0.1.2.dist-info/WHEEL
llm_dot_py-0.1.2.dist-info/top_level.txt
llm_dot_py-0.1.2.dist-info/RECORD
