Metadata-Version: 2.4
Name: llm-dot-py
Version: 0.1.2
Summary: A modular, block-by-block LLM building library
Author-email: nnul <hayetemxd88@gmail.com>
License: MIT
Classifier: Development Status :: 3 - Alpha
Classifier: Intended Audience :: Developers
Classifier: License :: OSI Approved :: MIT License
Classifier: Programming Language :: Python :: 3
Requires-Python: >=3.9
Requires-Dist: torch>=2.0.0
